<?xml version="1.0" encoding="UTF-8" standalone="yes"?>
<idPkg:Story xmlns:idPkg="http://ns.adobe.com/AdobeInDesign/idml/1.0/packaging" DOMVersion="14.0">
	<Story Self="u3fd" UserText="true" IsEndnoteStory="false" AppliedTOCStyle="n" TrackChanges="false" StoryTitle="$ID/" AppliedNamedGrid="n">
		<StoryPreference OpticalMarginAlignment="false" OpticalMarginSize="12" FrameType="TextFrameType" StoryOrientation="Horizontal" StoryDirection="LeftToRightDirection" />
		<InCopyExportOption IncludeGraphicProxies="true" IncludeAllResources="false" />
		<ParagraphStyleRange AppliedParagraphStyle="ParagraphStyle/New Initiates Footer">
			<CharacterStyleRange AppliedCharacterStyle="CharacterStyle/$ID/[No character style]">
				<Content>Congratulations, brothers!</Content>
				<Br />
			</CharacterStyleRange>
		</ParagraphStyleRange>
		<ParagraphStyleRange AppliedParagraphStyle="ParagraphStyle/New Initiates Subheader">
			<CharacterStyleRange AppliedCharacterStyle="CharacterStyle/$ID/[No character style]">
				<Content>The next initiation will be on </Content>
			</CharacterStyleRange>
			<CharacterStyleRange AppliedCharacterStyle="CharacterStyle/$ID/[No character style]" PageNumberType="TextVariable">
				<TextVariableInstance Self="u440" Name="Initiation Date" ResultText="Month #" AssociatedTextVariable="dTextVariablenInitiation Date" />
			</CharacterStyleRange>
			<CharacterStyleRange AppliedCharacterStyle="CharacterStyle/$ID/[No character style]">
				<Content>.</Content>
			</CharacterStyleRange>
		</ParagraphStyleRange>
	</Story>
</idPkg:Story>
